<annotation>
	<folder>testing</folder>
	<filename>1571095_0.jpg</filename>
	<path>C:\Users\97252\Desktop\Coding\License plate deep learning\testing\1571095_0.jpg</path>
	<source>
		<database>Unknown</database>
	</source>
	<size>
		<width>400</width>
		<height>287</height>
		<depth>3</depth>
	</size>
	<segmented>0</segmented>
	<object>
		<name>licence</name>
		<pose>Unspecified</pose>
		<truncated>0</truncated>
		<difficult>0</difficult>
		<bndbox>
			<xmin>114</xmin>
			<ymin>238</ymin>
			<xmax>247</xmax>
			<ymax>273</ymax>
		</bndbox>
	</object>
</annotation>
